pkdx/__init__.py
pkdx/cli.py
pkdx/defi.py
pkdx-0.1.0.dist-info/METADATA
pkdx-0.1.0.dist-info/WHEEL
pkdx-0.1.0.dist-info/entry_points.txt
pkdx-0.1.0.dist-info/top_level.txt
pkdx-0.1.0.dist-info/RECORD
