Metadata-Version: 2.4
Name: pkdx
Version: 0.1.0
Summary: CLI Pokedex
Author: Ophelia Van Wye
License: MIT
Requires-Dist: click
Requires-Dist: deep-translator
